jupyternetes_models/__init__.py
jupyternetes_models/_version.py
jupyternetes_models/models/__init__.py
jupyternetes_models/models/jupyter/__init__.py
jupyternetes_models/models/jupyter/notebook/__init__.py
jupyternetes_models/models/jupyter/notebook/instance/__init__.py
jupyternetes_models/models/jupyter/notebook/instance/v1_jupyter_notebook_instance.py
jupyternetes_models/models/jupyter/notebook/instance/v1_jupyter_notebook_instance_list.py
jupyternetes_models/models/jupyter/notebook/instance/v1_jupyter_notebook_instance_spec.py
jupyternetes_models/models/jupyter/notebook/instance/v1_jupyter_notebook_instance_spec_template.py
jupyternetes_models/models/jupyter/notebook/instance/v1_jupyter_notebook_instance_status.py
jupyternetes_models/models/jupyter/notebook/instance/v1_jupyter_notebook_instance_status_resourcestate.py
jupyternetes_models/models/kubernetes/__init__.py
jupyternetes_models/models/kubernetes/v1_listmeta.py
jupyternetes_models/models/kubernetes/v1_managedfields_entry.py
jupyternetes_models/models/kubernetes/v1_objectmeta.py
jupyternetes_models/models/kubernetes/v1_owner_reference.py
jupyternetes_models/unit_test/__init__.py
jupyternetes_models/unit_test/mockers.py
jupyternetes_models/unit_test/test_notebook_instance.py
jupyternetes_models-0.1.82.dist-info/METADATA
jupyternetes_models-0.1.82.dist-info/WHEEL
jupyternetes_models-0.1.82.dist-info/RECORD
